csv_wrangler/__init__.py
csv_wrangler/exporter.py
csv_wrangler/test_exporter.py
csv_wrangler/__pycache__/__init__.cpython-36.pyc
csv_wrangler/__pycache__/exporter.cpython-36.pyc
csv_wrangler/__pycache__/test_exporter.cpython-36.pyc
csv_wrangler-1.0.0.dist-info/LICENSE
csv_wrangler-1.0.0.dist-info/METADATA
csv_wrangler-1.0.0.dist-info/WHEEL
csv_wrangler-1.0.0.dist-info/top_level.txt
csv_wrangler-1.0.0.dist-info/RECORD
